nautilus_open_any_terminal/__init__.py
nautilus_open_any_terminal/nautilus_open_any_terminal.py
nautilus_open_any_terminal/locale/Makefile
nautilus_open_any_terminal/locale/ar.mo
nautilus_open_any_terminal/locale/ar.po
nautilus_open_any_terminal/locale/bn.mo
nautilus_open_any_terminal/locale/bn.po
nautilus_open_any_terminal/locale/cs.mo
nautilus_open_any_terminal/locale/cs.po
nautilus_open_any_terminal/locale/da.mo
nautilus_open_any_terminal/locale/da.po
nautilus_open_any_terminal/locale/de.mo
nautilus_open_any_terminal/locale/de.po
nautilus_open_any_terminal/locale/el.mo
nautilus_open_any_terminal/locale/el.po
nautilus_open_any_terminal/locale/es.mo
nautilus_open_any_terminal/locale/es.po
nautilus_open_any_terminal/locale/fa.mo
nautilus_open_any_terminal/locale/fa.po
nautilus_open_any_terminal/locale/fi.mo
nautilus_open_any_terminal/locale/fi.po
nautilus_open_any_terminal/locale/fr.mo
nautilus_open_any_terminal/locale/fr.po
nautilus_open_any_terminal/locale/gl.mo
nautilus_open_any_terminal/locale/gl.po
nautilus_open_any_terminal/locale/he.mo
nautilus_open_any_terminal/locale/he.po
nautilus_open_any_terminal/locale/hi.mo
nautilus_open_any_terminal/locale/hi.po
nautilus_open_any_terminal/locale/hu.mo
nautilus_open_any_terminal/locale/hu.po
nautilus_open_any_terminal/locale/id.mo
nautilus_open_any_terminal/locale/id.po
nautilus_open_any_terminal/locale/it.mo
nautilus_open_any_terminal/locale/it.po
nautilus_open_any_terminal/locale/ja.mo
nautilus_open_any_terminal/locale/ja.po
nautilus_open_any_terminal/locale/ko.mo
nautilus_open_any_terminal/locale/ko.po
nautilus_open_any_terminal/locale/nb.mo
nautilus_open_any_terminal/locale/nb.po
nautilus_open_any_terminal/locale/nl.mo
nautilus_open_any_terminal/locale/nl.po
nautilus_open_any_terminal/locale/pl.mo
nautilus_open_any_terminal/locale/pl.po
nautilus_open_any_terminal/locale/pt.mo
nautilus_open_any_terminal/locale/pt.po
nautilus_open_any_terminal/locale/pt_BR.mo
nautilus_open_any_terminal/locale/pt_BR.po
nautilus_open_any_terminal-0.8.1.dist-info/licenses/LICENSE
nautilus_open_any_terminal-0.8.1.dist-info/METADATA
nautilus_open_any_terminal-0.8.1.dist-info/WHEEL
nautilus_open_any_terminal-0.8.1.dist-info/top_level.txt
nautilus_open_any_terminal-0.8.1.dist-info/RECORD
