Metadata-Version: 2.4
Name: nautilus-open-any-terminal
Version: 0.8.1
Summary: an extension for nautilus, which adds an context-entry for opening other terminal emulators than gnome-terminal.
Author-email: Felix Buehler <account@buehler.rocks>
License:                     GNU GENERAL PUBLIC LICENSE
Keywords: nautilus,extension,terminal,gnome
Requires-Python: >=3.9
License-File: LICENSE
Dynamic: license-file
